opencensus/__init__.py
opencensus/ext/__init__.py
opencensus/ext/stackdriver/__init__.py
opencensus/ext/stackdriver/stats_exporter/__init__.py
opencensus/ext/stackdriver/trace_exporter/__init__.py
opencensus_ext_stackdriver-0.8.0.dist-info/METADATA
opencensus_ext_stackdriver-0.8.0.dist-info/WHEEL
opencensus_ext_stackdriver-0.8.0.dist-info/namespace_packages.txt
opencensus_ext_stackdriver-0.8.0.dist-info/top_level.txt
opencensus_ext_stackdriver-0.8.0.dist-info/RECORD
