Metadata-Version: 1.2
Name: opencensus-ext-stackdriver
Version: 0.8.0
Summary: OpenCensus Stackdriver Trace Exporter
Home-page: https://github.com/census-instrumentation/opencensus-python/tree/master/contrib/opencensus-ext-stackdriver
Author: OpenCensus Authors
Author-email: census-developers@googlegroups.com
License: Apache-2.0
Platform: UNKNOWN
Classifier: Intended Audience :: Developers
Classifier: Development Status :: 3 - Alpha
Classifier: Intended Audience :: Developers
Classifier: License :: OSI Approved :: Apache Software License
Classifier: Programming Language :: Python
Classifier: Programming Language :: Python :: 3
Classifier: Programming Language :: Python :: 3.6
Classifier: Programming Language :: Python :: 3.7
Classifier: Programming Language :: Python :: 3.8
Classifier: Programming Language :: Python :: 3.9
Requires-Python: >=3.6
